drift_detect/__init__.py
drift_detect/main.py
drift_detect-0.1.2.dist-info/METADATA
drift_detect-0.1.2.dist-info/WHEEL
drift_detect-0.1.2.dist-info/entry_points.txt
drift_detect-0.1.2.dist-info/top_level.txt
drift_detect-0.1.2.dist-info/RECORD
