Metadata-Version: 2.2
Name: drift_detect
Version: 0.1.2
Requires-Dist: numpy>=2.2.3
Requires-Dist: pandas>=2.2.3
Requires-Dist: scipy>=1.15.2
Dynamic: description
Dynamic: description-content-type
Dynamic: requires-dist
